truth/__init__.py
truth/main.py
TruthThn-0.0.2.dist-info/LICENSE
TruthThn-0.0.2.dist-info/METADATA
TruthThn-0.0.2.dist-info/WHEEL
TruthThn-0.0.2.dist-info/top_level.txt
TruthThn-0.0.2.dist-info/RECORD
