Metadata-Version: 2.1
Name: TruthThn
Version: 0.0.2
Summary: Создание таблиц истинности по функциям
Author-email: Ivan <iven.thn@gmail.com>
Classifier: Programming Language :: Python :: 3
Classifier: License :: OSI Approved :: MIT License
Classifier: Operating System :: OS Independent
Requires-Python: >=3.9.0
License-File: LICENSE
